seismic_classifier/__init__.py
seismic_classifier/ai/__init__.py
seismic_classifier/ai/create-picking_dataset.py
seismic_classifier/ai/create_classification_dataset.py
seismic_classifier/ai/database.py
seismic_classifier/ai/dataset.py
seismic_classifier/ai/event_type_lookup.py
seismic_classifier/ai/model.py
seismic_classifier/ai/params.py
seismic_classifier/ai/resnet1d.py
seismic_classifier/ai/spectrogram.py
seismic_classifier/api/__init__.py
seismic_classifier/api/rest/__init__.py
seismic_classifier/api/rest/client.py
seismic_classifier/api/rest/models.py
seismic_classifier/api/rest/server.py
seismic_classifier/core/__init__.py
seismic_classifier/core/classifier.py
seismic_classifier/core/utils.py
seismic_classifier/scripts/00_create_dataset.py
seismic_classifier/scripts/00_fetch_data_from_esg.py
seismic_classifier/scripts/01_train_model.py
seismic_classifier/scripts/02_test.py
seismic_classifier/scripts/__init__.py
seismic_classifier/scripts/test_merge_file.py
seismic_classifier/settings/__init__.py
seismic_classifier/settings/classifier_settings_template.toml
seismic_classifier-0.2.8.dist-info/entry_points.txt
seismic_classifier-0.2.8.dist-info/METADATA
seismic_classifier-0.2.8.dist-info/WHEEL
seismic_classifier-0.2.8.dist-info/RECORD
