Metadata-Version: 2.1
Name: seismic-classifier
Version: 0.2.8
Summary: trace by trace seismic classification
Author: Jean-Philippe Mercier
Author-email: jp.mercier@esgsolutions.com
Requires-Python: >=3.9,<3.12
Classifier: Programming Language :: Python :: 3
Classifier: Programming Language :: Python :: 3.9
Classifier: Programming Language :: Python :: 3.10
Classifier: Programming Language :: Python :: 3.11
Requires-Dist: aiohttp (>=3.8.4,<4.0.0)
Requires-Dist: faust (>=1.10.4,<2.0.0)
Requires-Dist: gdown (>=4.7.1,<5.0.0)
Requires-Dist: ipdb (>=0.13.13,<0.14.0)
Requires-Dist: ipython (>=8.13.2,<9.0.0)
Requires-Dist: multiprocess (>=0.70.14,<0.71.0)
Requires-Dist: numpy (>=1.24.3,<2.0.0)
Requires-Dist: pickled-carrots (>=0.1.1,<0.2.0)
Requires-Dist: quilt (>=2.9.15,<3.0.0)
Requires-Dist: quilt3 (>=5.3.1,<6.0.0)
Requires-Dist: torch (>=2.0.1,<3.0.0)
Requires-Dist: torchaudio (>=2.0.2,<3.0.0)
Requires-Dist: torchvision (>=0.15.2,<0.16.0)
Requires-Dist: useis (>=1.0.2,<2.0.0)
